riddle/Locket.py
riddle/Riddle.py
riddle/SecretKeeper.py
riddle/__init__.py
riddle/encrypt.py
riddle-2020.7.26.dist-info/LICENSE
riddle-2020.7.26.dist-info/METADATA
riddle-2020.7.26.dist-info/WHEEL
riddle-2020.7.26.dist-info/top_level.txt
riddle-2020.7.26.dist-info/zip-safe
riddle-2020.7.26.dist-info/RECORD
