Metadata-Version: 2.1
Name: riddle
Version: 2020.7.26
Summary: Python library for encryption
Home-page: https://github.com/idin/riddle
Author: Idin
Author-email: py@idin.ca
License: MIT
Keywords: encryption decryption
Platform: UNKNOWN
Classifier: Development Status :: 3 - Alpha
Classifier: Intended Audience :: Developers
Classifier: Programming Language :: Python :: 3 :: Only
Classifier: Programming Language :: Python :: 3.6
Classifier: Programming Language :: Python :: 3.7
Classifier: Topic :: Software Development :: Libraries :: Python Modules
Requires-Python: ~=3.6
Requires-Dist: dill
Requires-Dist: disk
Requires-Dist: pandas
Requires-Dist: chronometry
Requires-Dist: slytherin
